pytest_bdd_reporter/__init__.py
pytest_bdd_reporter/cli.py
pytest_bdd_reporter/email_reporter.py
pytest_bdd_reporter/hooks.py
pytest_bdd_reporter/plugin.py
pytest_bdd_reporter/reporter.py
pytest_bdd_reporter/status_manager.py
pytest_bdd_reporter/suite_manager.py
pytest_bdd_reporter/templates/__init__.py
pytest_bdd_reporter/templates/email_report.html
pytest_bdd_reporter/templates/email_summary.html
pytest_bdd_reporter/templates/log.html
pytest_bdd_reporter/templates/report.html
pytest_bdd_reporter/templates/status_management.js
pytest_bdd_reporter/templates/text_email_report.html
pytest_bdd_reporter-1.0.0.dist-info/licenses/LICENSE
pytest_bdd_reporter-1.0.0.dist-info/METADATA
pytest_bdd_reporter-1.0.0.dist-info/WHEEL
pytest_bdd_reporter-1.0.0.dist-info/entry_points.txt
pytest_bdd_reporter-1.0.0.dist-info/top_level.txt
pytest_bdd_reporter-1.0.0.dist-info/RECORD
