Metadata-Version: 2.4
Name: pytest-bdd-reporter
Version: 1.0.0
Summary: Enterprise-grade BDD test reporting with interactive dashboards, suite management, and comprehensive email integration
Home-page: https://github.com/ashisays/pytest-bdd-reporter
Author: Ashish Pundir
Author-email: Ashish Pundir <pundir.ashish@live.com>
Maintainer-email: Ashish Pundir <pundir.ashish@live.com>
License: MIT
Project-URL: Homepage, https://github.com/ashisays/pytest-bdd-reporter
Project-URL: Repository, https://github.com/ashisays/pytest-bdd-reporter
Project-URL: Documentation, https://github.com/ashisays/pytest-bdd-reporter#readme
Project-URL: Bug Tracker, https://github.com/ashisays/pytest-bdd-reporter/issues
Keywords: pytest,bdd,testing,reporting,dashboard,email,suite
Classifier: Development Status :: 5 - Production/Stable
Classifier: Framework :: Pytest
Classifier: Intended Audience :: Developers
Classifier: Intended Audience :: Information Technology
Classifier: License :: OSI Approved :: MIT License
Classifier: Operating System :: OS Independent
Classifier: Programming Language :: Python :: 3
Classifier: Programming Language :: Python :: 3.7
Classifier: Programming Language :: Python :: 3.8
Classifier: Programming Language :: Python :: 3.9
Classifier: Programming Language :: Python :: 3.10
Classifier: Programming Language :: Python :: 3.11
Classifier: Programming Language :: Python :: 3.12
Classifier: Topic :: Software Development :: Testing
Classifier: Topic :: Software Development :: Quality Assurance
Classifier: Topic :: Internet :: WWW/HTTP :: Dynamic Content
Classifier: Topic :: Text Processing :: Markup :: HTML
Requires-Python: >=3.7
License-File: LICENSE
Requires-Dist: pytest>=6.0.0
Requires-Dist: pytest-bdd>=6.0.0
Requires-Dist: jinja2>=3.0.0
Provides-Extra: dev
Requires-Dist: pytest-cov; extra == "dev"
Requires-Dist: black; extra == "dev"
Requires-Dist: flake8; extra == "dev"
Requires-Dist: mypy; extra == "dev"
Requires-Dist: build; extra == "dev"
Requires-Dist: twine; extra == "dev"
Dynamic: author
Dynamic: home-page
Dynamic: license-file
Dynamic: requires-python
